Metadata-Version: 2.4
Name: cxroots
Version: 3.2.0
Summary: Find all the roots (zeros) of a complex analytic function within a given contour in the complex plane.
Author-email: Robert Parini <robert.parini@gmail.com>
License: BSD-3-Clause
Project-URL: Homepage, https://rparini.github.io/cxroots/
Project-URL: Documentation, https://rparini.github.io/cxroots/
Project-URL: Repository, https://github.com/rparini/cxroots
Project-URL: Issues, https://github.com/rparini/cxroots/issues
Project-URL: Changelog, https://github.com/rparini/cxroots/blob/master/changelog.md
Keywords: roots,zeros,complex,analytic,functions
Classifier: Development Status :: 5 - Production/Stable
Classifier: Intended Audience :: Science/Research
Classifier: Topic :: Scientific/Engineering :: Mathematics
Classifier: License :: OSI Approved :: BSD License
Classifier: Programming Language :: Python :: 3 :: Only
Requires-Python: >=3.10
License-File: LICENSE
Requires-Dist: numpy
Requires-Dist: scipy
Requires-Dist: numpydoc
Requires-Dist: mpmath
Requires-Dist: rich
Provides-Extra: plot
Requires-Dist: matplotlib; extra == "plot"
Dynamic: license-file
